lagrange/lagrange.py
lagrange_udav318-0.1.0.dist-info/METADATA
lagrange_udav318-0.1.0.dist-info/WHEEL
lagrange_udav318-0.1.0.dist-info/top_level.txt
lagrange_udav318-0.1.0.dist-info/RECORD
